Metadata-Version: 2.1
Name: plover-minimal-english-stenotype
Version: 1.1.0
Summary: Plover English stenotype system plug-in with no automatic unfolding of orthography rules
Home-page: https://github.com/EPLHREU/plover-minimal-english-stenotype
Author: Emily Easteal
Author-email: emily@easteal.dev
License: UNKNOWN
Keywords: plover plover_plugin
Platform: UNKNOWN
Classifier: Programming Language :: Python :: 3.6
Classifier: Programming Language :: Python :: 3.7
Classifier: Programming Language :: Python :: 3.8
Classifier: Programming Language :: Python :: 3.9
